allowdynamic/__init__.py
allowdynamic/__main__.py
allowdynamic/container.py
allowdynamic-2.0.1.dist-info/licenses/LICENSE
allowdynamic-2.0.1.dist-info/METADATA
allowdynamic-2.0.1.dist-info/WHEEL
allowdynamic-2.0.1.dist-info/top_level.txt
allowdynamic-2.0.1.dist-info/RECORD
