Metadata-Version: 2.4
Name: allowdynamic
Version: 2.0.1
Summary: Dynamic variables in Python
Author: DiamondGotCat
License: MIT License
Project-URL: Homepage, https://github.com/DiamondGotCat/allowdynamic
Classifier: Programming Language :: Python :: 3
Classifier: License :: OSI Approved :: MIT License
Classifier: Operating System :: OS Independent
License-File: LICENSE
Dynamic: license-file
